metabengine/.DS_Store
metabengine/__init__.py
metabengine/alignment.py
metabengine/ann_feat_quality.py
metabengine/annotation.py
metabengine/feature_grouping.py
metabengine/normalization.py
metabengine/params.py
metabengine/peak_detect.py
metabengine/raw_data_utils.py
metabengine/stats.py
metabengine/utils_functions.py
metabengine/visualization.py
metabengine/workflows.py
metabengine/data/isotopes.txt
metabengine/data/lipid_istd_neg.json
metabengine/data/lipid_istd_pos.json
metabengine/data/metabolite_istd_neg.json
metabengine/data/metabolite_istd_pos.json
metabengine/model/.DS_Store
metabengine/model/peak_quality_NN.h5
metabengine/model/peak_quality_NN.keras
metabengine-0.0.19.dist-info/METADATA
metabengine-0.0.19.dist-info/WHEEL
metabengine-0.0.19.dist-info/licenses/LICENSE
metabengine-0.0.19.dist-info/RECORD
