Metadata-Version: 2.1
Name: metabengine
Version: 0.0.19
Summary: Data preprocessing for mass spectrometry-based metabolomics data
Project-URL: Homepage, https://github.com/Waddlessss/metabengine
Author-email: Huaxu Yu <yhxchem@outlook.com>
Maintainer-email: Huaxu Yu <yhxchem@outlook.com>
License-File: LICENSE
Classifier: License :: OSI Approved :: MIT License
Classifier: Operating System :: OS Independent
Classifier: Programming Language :: Python :: 3
Requires-Python: >=3.8
Requires-Dist: lxml>=4.9.2
Requires-Dist: matplotlib
Requires-Dist: ms-entropy>=1.1.1
Requires-Dist: networkx
Requires-Dist: numpy>=1.24
Requires-Dist: pandas>=2.0
Requires-Dist: pyteomics>=4.6
Requires-Dist: scipy>=1.10.1
Requires-Dist: tensorflow>=2.12.0
Requires-Dist: tqdm>=4.65.0
